mewpy/__init__.py
mewpy/logger.py
mewpy/cobra/__init__.py
mewpy/cobra/medium.py
mewpy/cobra/parsimonious.py
mewpy/cobra/util.py
mewpy/com/__init__.py
mewpy/com/analysis.py
mewpy/com/com.py
mewpy/com/regfba.py
mewpy/com/similarity.py
mewpy/com/steadycom.py
mewpy/germ/__init__.py
mewpy/germ/algebra/__init__.py
mewpy/germ/algebra/algebra_constants.py
mewpy/germ/algebra/algebra_utils.py
mewpy/germ/algebra/expression.py
mewpy/germ/algebra/parsing.py
mewpy/germ/algebra/symbolic.py
mewpy/germ/analysis/__init__.py
mewpy/germ/analysis/analysis_utils.py
mewpy/germ/analysis/coregflux.py
mewpy/germ/analysis/fba.py
mewpy/germ/analysis/integrated_analysis.py
mewpy/germ/analysis/metabolic_analysis.py
mewpy/germ/analysis/pfba.py
mewpy/germ/analysis/prom.py
mewpy/germ/analysis/regulatory_analysis.py
mewpy/germ/analysis/rfba.py
mewpy/germ/analysis/srfba.py
mewpy/germ/models/__init__.py
mewpy/germ/models/backends.py
mewpy/germ/models/factories.py
mewpy/germ/models/metabolic.py
mewpy/germ/models/model.py
mewpy/germ/models/regulatory.py
mewpy/germ/models/regulatory_extension.py
mewpy/germ/models/serialization.py
mewpy/germ/models/simulator_model.py
mewpy/germ/models/unified_factory.py
mewpy/germ/solution/__init__.py
mewpy/germ/solution/multi_solution.py
mewpy/germ/solution/summary.py
mewpy/germ/variables/__init__.py
mewpy/germ/variables/gene.py
mewpy/germ/variables/interaction.py
mewpy/germ/variables/metabolite.py
mewpy/germ/variables/reaction.py
mewpy/germ/variables/regulator.py
mewpy/germ/variables/target.py
mewpy/germ/variables/variable.py
mewpy/germ/variables/variables_utils.py
mewpy/io/__init__.py
mewpy/io/builder.py
mewpy/io/director.py
mewpy/io/dto.py
mewpy/io/reader.py
mewpy/io/sbml.py
mewpy/io/writer.py
mewpy/io/engines/__init__.py
mewpy/io/engines/boolean_csv.py
mewpy/io/engines/co_expression_csv.py
mewpy/io/engines/cobra_model.py
mewpy/io/engines/engine.py
mewpy/io/engines/engines_utils.py
mewpy/io/engines/json.py
mewpy/io/engines/metabolic_sbml.py
mewpy-1.0.0.dist-info/licenses/LICENSE
mewpy-1.0.0.dist-info/METADATA
mewpy-1.0.0.dist-info/WHEEL
mewpy-1.0.0.dist-info/top_level.txt
mewpy-1.0.0.dist-info/zip-safe
mewpy-1.0.0.dist-info/RECORD
