Metadata-Version: 2.4
Name: mewpy
Version: 1.0.0
Summary: MEWpy - Metabolic Engineering in Python
Author: BiSBII CEB University of Minho
Author-email: Vitor Pereira <vmspereira@gmail.com>
Maintainer-email: Vitor Pereira <vmspereira@gmail.com>
License-Expression: GPL-3.0-or-later
Project-URL: Homepage, https://github.com/BioSystemsUM/mewpy/
Project-URL: Repository, https://github.com/vmspereira/mewpy/
Project-URL: Development, https://github.com/vmspereira/MEWpy
Project-URL: Documentation, https://mewpy.readthedocs.io
Project-URL: Issues, https://github.com/vmspereira/mewpy/issues
Keywords: metabolism,biology,constraint-based,optimization,flux-balance analysis,strain optimization
Classifier: Development Status :: 5 - Production/Stable
Classifier: Intended Audience :: Science/Research
Classifier: Operating System :: OS Independent
Classifier: Programming Language :: Python :: 3
Classifier: Programming Language :: Python :: 3.8
Classifier: Programming Language :: Python :: 3.9
Classifier: Programming Language :: Python :: 3.10
Classifier: Programming Language :: Python :: 3.11
Classifier: Programming Language :: Python :: 3.12
Classifier: Topic :: Scientific/Engineering :: Bio-Informatics
Requires-Python: >=3.8
License-File: LICENSE
Requires-Dist: numpy>=1.26.0
Requires-Dist: cobra
Requires-Dist: reframed
Requires-Dist: inspyred
Requires-Dist: jmetalpy>=1.5.0
Requires-Dist: networkx
Requires-Dist: matplotlib
Requires-Dist: tqdm
Requires-Dist: joblib
Requires-Dist: httpx
Requires-Dist: pandas
Requires-Dist: numexpr
Requires-Dist: ray>=2.0.0
Provides-Extra: scip
Requires-Dist: pyscipopt>=5.0.0; extra == "scip"
Provides-Extra: solvers
Requires-Dist: pyscipopt>=5.0.0; extra == "solvers"
Provides-Extra: germ
Requires-Dist: scikit-learn>=1.0.0; extra == "germ"
Requires-Dist: scipy>=1.7.0; extra == "germ"
Provides-Extra: test
Requires-Dist: pytest>=6.0; extra == "test"
Requires-Dist: pytest-runner; extra == "test"
Requires-Dist: cplex; extra == "test"
Requires-Dist: tox; extra == "test"
Requires-Dist: pyscipopt>=5.0.0; extra == "test"
Requires-Dist: scikit-learn>=1.0.0; extra == "test"
Requires-Dist: scipy>=1.7.0; extra == "test"
Provides-Extra: dev
Requires-Dist: pytest>=6.0; extra == "dev"
Requires-Dist: pytest-runner; extra == "dev"
Requires-Dist: cplex; extra == "dev"
Requires-Dist: tox; extra == "dev"
Requires-Dist: flake8; extra == "dev"
Requires-Dist: black; extra == "dev"
Requires-Dist: isort; extra == "dev"
Requires-Dist: scikit-learn>=1.0.0; extra == "dev"
Requires-Dist: scipy>=1.7.0; extra == "dev"
Provides-Extra: docs
Requires-Dist: sphinx; extra == "docs"
Requires-Dist: sphinx-rtd-theme; extra == "docs"
Dynamic: license-file
